tree_sitter_less/__init__.py
tree_sitter_less/__init__.pyi
tree_sitter_less/_binding.pyd
tree_sitter_less/binding.c
tree_sitter_less/py.typed
tree_sitter_less/queries/highlights.scm
tree_sitter_less-1.0.0.dist-info/METADATA
tree_sitter_less-1.0.0.dist-info/WHEEL
tree_sitter_less-1.0.0.dist-info/top_level.txt
tree_sitter_less-1.0.0.dist-info/RECORD
