Metadata-Version: 2.1
Name: tree-sitter-less
Version: 1.0.0
Summary: LESS grammar for tree-sitter
Author-email: Jimliang <jimlianglinux@gmail.com>
License: MIT
Project-URL: Homepage, https://github.com/jimliang/tree-sitter-less
Keywords: incremental,parsing,tree-sitter,less
Classifier: Intended Audience :: Developers
Classifier: License :: OSI Approved :: MIT License
Classifier: Topic :: Software Development :: Compilers
Classifier: Topic :: Text Processing :: Linguistic
Classifier: Typing :: Typed
Requires-Python: >=3.8
Provides-Extra: core
Requires-Dist: tree-sitter ~=0.21 ; extra == 'core'
